sample/__init__.py
sample/driver.py
sample/filepath.py
sample/package_data.dat
sel2driver-0.0.1.data/data/my_data/data_file
sel2driver-0.0.1.dist-info/LICENSE.txt
sel2driver-0.0.1.dist-info/METADATA
sel2driver-0.0.1.dist-info/WHEEL
sel2driver-0.0.1.dist-info/entry_points.txt
sel2driver-0.0.1.dist-info/top_level.txt
sel2driver-0.0.1.dist-info/RECORD
